bruno_abilities/__init__.py
bruno_abilities/abilities/__init__.py
bruno_abilities/abilities/alarm_ability.py
bruno_abilities/abilities/music_ability.py
bruno_abilities/abilities/notes_ability.py
bruno_abilities/abilities/reminder_ability.py
bruno_abilities/abilities/timer_ability.py
bruno_abilities/abilities/todo_ability.py
bruno_abilities/base/__init__.py
bruno_abilities/base/ability_base.py
bruno_abilities/base/decorators.py
bruno_abilities/base/metadata.py
bruno_abilities/base/parameter_extractor.py
bruno_abilities/infrastructure/__init__.py
bruno_abilities/infrastructure/state_manager.py
bruno_abilities/registry/__init__.py
bruno_abilities/registry/discovery.py
bruno_abilities/registry/lifecycle.py
bruno_abilities/registry/registry.py
bruno_abilities/schemas/__init__.py
bruno_abilities/schemas/music_schema.py
bruno_abilities/schemas/notes_schema.py
bruno_abilities/schemas/todo_schema.py
bruno_abilities/validation/__init__.py
bruno_abilities/validation/error_messages.py
bruno_abilities/validation/models.py
bruno_abilities/validation/validators.py
bruno_abilities-1.0.0.dist-info/licenses/LICENSE
bruno_abilities-1.0.0.dist-info/METADATA
bruno_abilities-1.0.0.dist-info/WHEEL
bruno_abilities-1.0.0.dist-info/entry_points.txt
bruno_abilities-1.0.0.dist-info/top_level.txt
bruno_abilities-1.0.0.dist-info/RECORD
