Metadata-Version: 2.4
Name: bruno-abilities
Version: 1.0.0
Summary: Action execution layer for Bruno Personal Assistant
Author-email: Meggy AI <contact@meggy-ai.com>
License-Expression: MIT
Project-URL: Homepage, https://github.com/meggy-ai/bruno-abilities
Project-URL: Documentation, https://bruno-abilities.readthedocs.io
Project-URL: Repository, https://github.com/meggy-ai/bruno-abilities
Project-URL: Issues, https://github.com/meggy-ai/bruno-abilities/issues
Keywords: bruno,ai,assistant,abilities,automation
Classifier: Development Status :: 3 - Alpha
Classifier: Intended Audience :: Developers
Classifier: Programming Language :: Python :: 3
Classifier: Programming Language :: Python :: 3.10
Classifier: Programming Language :: Python :: 3.11
Classifier: Programming Language :: Python :: 3.12
Classifier: Topic :: Software Development :: Libraries :: Python Modules
Requires-Python: >=3.10
License-File: LICENSE
Requires-Dist: bruno-core>=0.1.0
Requires-Dist: bruno-llm>=0.1.0
Requires-Dist: bruno-memory>=0.1.0
Requires-Dist: pydantic>=2.0.0
Requires-Dist: structlog>=23.0.0
Requires-Dist: python-dateutil>=2.8.0
Requires-Dist: dateparser>=1.1.0
Requires-Dist: pytz>=2023.3
Provides-Extra: music
Requires-Dist: pygame>=2.5.0; extra == "music"
Provides-Extra: dev
Requires-Dist: pytest>=7.4.0; extra == "dev"
Requires-Dist: pytest-asyncio>=0.21.0; extra == "dev"
Requires-Dist: pytest-mock>=3.11.0; extra == "dev"
Requires-Dist: pytest-cov>=4.1.0; extra == "dev"
Requires-Dist: ruff>=0.1.0; extra == "dev"
Requires-Dist: black>=23.0.0; extra == "dev"
Requires-Dist: isort>=5.12.0; extra == "dev"
Requires-Dist: mypy>=1.5.0; extra == "dev"
Requires-Dist: bandit>=1.7.5; extra == "dev"
Requires-Dist: safety>=2.3.0; extra == "dev"
Provides-Extra: docs
Requires-Dist: sphinx>=7.0.0; extra == "docs"
Requires-Dist: sphinx-rtd-theme>=1.3.0; extra == "docs"
Requires-Dist: sphinx-autodoc-typehints>=1.24.0; extra == "docs"
Dynamic: license-file
